Workbook

Sheet Methodology
B1: Mini-Project 2: Zero-Coupon Bond (ZCB) Yield Curve
B5: Data
B6: 353 U.S. Treasury notes and bonds quoted as of 9/4/2026 (maturities from 9/15/2026 out to 8/15/2056). Quoted bid/ask prices are Treasury 32nds-plus-eighths fractional quotes (e.g. a displayed 99.312 means 99 + (31 + 2/8)/32 = 99.9765625, not the literal decimal 99.312); both sides are decoded with that convention before use. The clean price is the decoded bid/ask midpoint. Accrued interest is computed from each bond's own semiannual coupon schedule using Excel's COUPDAYBS/COUPDAYS functions (Actual/Actual basis) and added to the clean price to obtain the dirty (invoice) price that equals the present value of the bond's cash flows.
B8: Cash-flow reconstruction
B9: For every bond, coupon dates were generated by stepping back six months at a time from the maturity date, preserving month-end dates whenever the maturity itself falls on the last day of a month (e.g. an 8/31 maturity generates 2/28 or 2/29, not 2/31-clipped-elsewhere dates). This gives a coupon of (coupon rate)/2 per $100 face every period, plus $100 principal at maturity. Across all 353 bonds this produces 245 distinct future payment dates spanning the full curve.
B11: Curve model
B12: Because the payment dates of different bonds do not fall on a common grid, a literal date-by-date bootstrap is not well identified, so the whole discount curve was estimated at once with the Nelson-Siegel-Svensson (NSS) functional form for the continuously-compounded zero rate:
B13: r(t) = β0 + β1·[(1-e^(-t/τ1))/(t/τ1)] + β2·[(1-e^(-t/τ1))/(t/τ1) - e^(-t/τ1)] + β3·[(1-e^(-t/τ2))/(t/τ2) - e^(-t/τ2)]
B15: Fitting
B16: The six NSS parameters (β0, β1, β2, β3, τ1, τ2) were chosen by nonlinear least squares (Python scipy, multistart with 60+ initial points converging to the same minimum) to minimize squared bond-price residuals against the corrected dirty prices. Repricing the 353 bonds with the fitted curve gives an RMSE of about $0.148 and a mean absolute error of about $0.089 per $100 face — well below the prior (mis-decoded) fit's $0.293 RMSE, because most of that earlier error was the quote-decoding bug, not curve-fitting noise. Quoted bid-ask spreads average about $0.045 (roughly one 32nd) and are not uniform across bonds (a mix of 1, 1.5 and 2 ticks), so residuals should still be read as a mix of smooth-curve approximation error and bond-specific richness/liquidity effects, not bid-ask noise alone.
B18: Output
B19: The fitted r(t) is evaluated (1) at each of the 245 distinct bond payment dates ('ZCB Curve - Payment Dates') and (2) on a smooth 0.1-year grid through 30 years ('ZCB Curve - Smooth Grid'). Discount factors are d(t)=exp(-r(t)t). Fitted zero rates rise from about 3.7% at the short end to roughly 5.3-5.4% around 20-25 years, with no negative segments. The raw Treasury quotes, decoded prices, and bond-level fit diagnostics are on 'Input Data'; the visible NSS parameters, validation metrics, and a note on what was corrected from the prior submission are on 'Fit Diagnostics'.

Sheet Input Data
A1: Maturity | B1: Coupon (%) | C1: Bid (quoted) | D1: Asked (quoted) | E1: Asked Yield (%) | F1: Bid (decimal) | G1: Asked (decimal) | H1: Clean Price | I1: Accrued Int. | J1: Dirty Price | K1: t (years) | L1: Model Dirty Price | M1: Pricing Error | N1: Absolute Error | O1: Model Clean Price | P1: Inside Bid-Ask? | R1: Settlement Date
A2: 46280 | B2: 4.625 | C2: 100 | D2: 100.01 | E2: 2.937 | F2: =INT(C2)+INT(ROUND((C2-INT(C2))*1000,0)/10)/32+MOD(ROUND((C2-INT(C2))*1000,0),10)/256 -> 100 | G2: =INT(D2)+INT(ROUND((D2-INT(D2))*1000,0)/10)/32+MOD(ROUND((D2-INT(D2))*1000,0),10)/256 -> 100.03125 | H2: =(F2+G2)/2 -> 100.01562 | I2: =(B2/2)*COUPDAYBS($R$2,A2,2,1)/COUPDAYS($R$2,A2,2,1) -> 2.1742527 | J2: =H2+I2 -> 102.18988 | K2: =(A2-$R$2)/365 -> 0.030136986 | L2: =SUMIF('Cash Flows'!$A$2:$A$5628,ROW(),'Cash Flows'!$E$2:$E$5628) -> 102.19681 | M2: =L2-J2 -> 0.0069365673 | N2: =ABS(M2) -> 0.0069365673 | O2: =L2-I2 -> 100.02256 | P2: =IF(AND(O2>=F2,O2<=G2),"Yes","No") -> Yes | R2: 46269
A3: 46295 | B3: 0.875 | C3: 99.256 | D3: 99.266 | E3: 3.625 | F3: =INT(C3)+INT(ROUND((C3-INT(C3))*1000,0)/10)/32+MOD(ROUND((C3-INT(C3))*1000,0),10)/256 -> 99.804688 | G3: =INT(D3)+INT(ROUND((D3-INT(D3))*1000,0)/10)/32+MOD(ROUND((D3-INT(D3))*1000,0),10)/256 -> 99.835938 | H3: =(F3+G3)/2 -> 99.820312 | I3: =(B3/2)*COUPDAYBS($R$2,A3,2,1)/COUPDAYS($R$2,A3,2,1) -> 0.37534153 | J3: =H3+I3 -> 100.19565 | K3: =(A3-$R$2)/365 -> 0.071232877 | L3: =SUMIF('Cash Flows'!$A$2:$A$5628,ROW(),'Cash Flows'!$E$2:$E$5628) -> 100.1676 | M3: =L3-J3 -> -0.02805017 | N3: =ABS(M3) -> 0.02805017 | O3: =L3-I3 -> 99.792262 | P3: =IF(AND(O3>=F3,O3<=G3),"Yes","No") -> No
A4: 46295 | B4: 1.625 | C4: 99.276 | D4: 99.286 | E4: 3.318 | F4: =INT(C4)+INT(ROUND((C4-INT(C4))*1000,0)/10)/32+MOD(ROUND((C4-INT(C4))*1000,0),10)/256 -> 99.867188 | G4: =INT(D4)+INT(ROUND((D4-INT(D4))*1000,0)/10)/32+MOD(ROUND((D4-INT(D4))*1000,0),10)/256 -> 99.898438 | H4: =(F4+G4)/2 -> 99.882812 | I4: =(B4/2)*COUPDAYBS($R$2,A4,2,1)/COUPDAYS($R$2,A4,2,1) -> 0.69706284 | J4: =H4+I4 -> 100.57988 | K4: =(A4-$R$2)/365 -> 0.071232877 | L4: =SUMIF('Cash Flows'!$A$2:$A$5628,ROW(),'Cash Flows'!$E$2:$E$5628) -> 100.5416 | M4: =L4-J4 -> -0.038279183 | N4: =ABS(M4) -> 0.038279183 | O4: =L4-I4 -> 99.844533 | P4: =IF(AND(O4>=F4,O4<=G4),"Yes","No") -> No
A5: 46295 | B5: 3.5 | C5: 99.306 | D5: 99.316 | E5: 3.603 | F5: =INT(C5)+INT(ROUND((C5-INT(C5))*1000,0)/10)/32+MOD(ROUND((C5-INT(C5))*1000,0),10)/256 -> 99.960938 | G5: =INT(D5)+INT(ROUND((D5-INT(D5))*1000,0)/10)/32+MOD(ROUND((D5-INT(D5))*1000,0),10)/256 -> 99.992188 | H5: =(F5+G5)/2 -> 99.976562 | I5: =(B5/2)*COUPDAYBS($R$2,A5,2,1)/COUPDAYS($R$2,A5,2,1) -> 1.5013661 | J5: =H5+I5 -> 101.47793 | K5: =(A5-$R$2)/365 -> 0.071232877 | L5: =SUMIF('Cash Flows'!$A$2:$A$5628,ROW(),'Cash Flows'!$E$2:$E$5628) -> 101.47658 | M5: =L5-J5 -> -0.0013517164 | N5: =ABS(M5) -> 0.0013517164 | O5: =L5-I5 -> 99.975211 | P5: =IF(AND(O5>=F5,O5<=G5),"Yes","No") -> Yes
A6: 46310 | B6: 4.625 | C6: 100.022 | D6: 100.032 | E6: 3.576 | F6: =INT(C6)+INT(ROUND((C6-INT(C6))*1000,0)/10)/32+MOD(ROUND((C6-INT(C6))*1000,0),10)/256 -> 100.07031 | G6: =INT(D6)+INT(ROUND((D6-INT(D6))*1000,0)/10)/32+MOD(ROUND((D6-INT(D6))*1000,0),10)/256 -> 100.10156 | H6: =(F6+G6)/2 -> 100.08594 | I6: =(B6/2)*COUPDAYBS($R$2,A6,2,1)/COUPDAYS($R$2,A6,2,1) -> 1.7943989 | J6: =H6+I6 -> 101.88034 | K6: =(A6-$R$2)/365 -> 0.11232877 | L6: =SUMIF('Cash Flows'!$A$2:$A$5628,ROW(),'Cash Flows'!$E$2:$E$5628) -> 101.8769 | M6: =L6-J6 -> -0.0034386583 | N6: =ABS(M6) -> 0.0034386583 | O6: =L6-I6 -> 100.0825 | P6: =IF(AND(O6>=F6,O6<=G6),"Yes","No") -> Yes
A7: 46326 | B7: 1.125 | C7: 99.186 | D7: 99.196 | E7: 3.808 | F7: =INT(C7)+INT(ROUND((C7-INT(C7))*1000,0)/10)/32+MOD(ROUND((C7-INT(C7))*1000,0),10)/256 -> 99.585938 | G7: =INT(D7)+INT(ROUND((D7-INT(D7))*1000,0)/10)/32+MOD(ROUND((D7-INT(D7))*1000,0),10)/256 -> 99.617188 | H7: =(F7+G7)/2 -> 99.601562 | I7: =(B7/2)*COUPDAYBS($R$2,A7,2,1)/COUPDAYS($R$2,A7,2,1) -> 0.38824728 | J7: =H7+I7 -> 99.98981 | K7: =(A7-$R$2)/365 -> 0.15616438 | L7: =SUMIF('Cash Flows'!$A$2:$A$5628,ROW(),'Cash Flows'!$E$2:$E$5628) -> 99.964209 | M7: =L7-J7 -> -0.025601236 | N7: =ABS(M7) -> 0.025601236 | O7: =L7-I7 -> 99.575961 | P7: =IF(AND(O7>=F7,O7<=G7),"Yes","No") -> No
A8: 46326 | B8: 1.625 | C8: 99.212 | D8: 99.222 | E8: 3.755 | F8: =INT(C8)+INT(ROUND((C8-INT(C8))*1000,0)/10)/32+MOD(ROUND((C8-INT(C8))*1000,0),10)/256 -> 99.664062 | G8: =INT(D8)+INT(ROUND((D8-INT(D8))*1000,0)/10)/32+MOD(ROUND((D8-INT(D8))*1000,0),10)/256 -> 99.695312 | H8: =(F8+G8)/2 -> 99.679688 | I8: =(B8/2)*COUPDAYBS($R$2,A8,2,1)/COUPDAYS($R$2,A8,2,1) -> 0.56080163 | J8: =H8+I8 -> 100.24049 | K8: =(A8-$R$2)/365 -> 0.15616438 | L8: =SUMIF('Cash Flows'!$A$2:$A$5628,ROW(),'Cash Flows'!$E$2:$E$5628) -> 100.21272 | M8: =L8-J8 -> -0.027767946 | N8: =ABS(M8) -> 0.027767946 | O8: =L8-I8 -> 99.65192 | P8: =IF(AND(O8>=F8,O8<=G8),"Yes","No") -> No
A9: 46326 | B9: 4.125 | C9: 100 | D9: 100.01 | E9: 3.877 | F9: =INT(C9)+INT(ROUND((C9-INT(C9))*1000,0)/10)/32+MOD(ROUND((C9-INT(C9))*1000,0),10)/256 -> 100 | G9: =INT(D9)+INT(ROUND((D9-INT(D9))*1000,0)/10)/32+MOD(ROUND((D9-INT(D9))*1000,0),10)/256 -> 100.03125 | H9: =(F9+G9)/2 -> 100.01562 | I9: =(B9/2)*COUPDAYBS($R$2,A9,2,1)/COUPDAYS($R$2,A9,2,1) -> 1.4235734 | J9: =H9+I9 -> 101.4392 | K9: =(A9-$R$2)/365 -> 0.15616438 | L9: =SUMIF('Cash Flows'!$A$2:$A$5628,ROW(),'Cash Flows'!$E$2:$E$5628) -> 101.45528 | M9: =L9-J9 -> 0.016086004 | N9: =ABS(M9) -> 0.016086004 | O9: =L9-I9 -> 100.03171 | P9: =IF(AND(O9>=F9,O9<=G9),"Yes","No") -> No
A10: 46341 | B10: 2 | C10: 99.204 | D10: 99.214 | E10: 3.787 | F10: =INT(C10)+INT(ROUND((C10-INT(C10))*1000,0)/10)/32+MOD(ROUND((C10-INT(C10))*1000,0),10)/256 -> 99.640625 | G10: =INT(D10)+INT(ROUND((D10-INT(D10))*1000,0)/10)/32+MOD(ROUND((D10-INT(D10))*1000,0),10)/256 -> 99.671875 | H10: =(F10+G10)/2 -> 99.65625 | I10: =(B10/2)*COUPDAYBS($R$2,A10,2,1)/COUPDAYS($R$2,A10,2,1) -> 0.60869565 | J10: =H10+I10 -> 100.26495 | K10: =(A10-$R$2)/365 -> 0.19726027 | L10: =SUMIF('Cash Flows'!$A$2:$A$5628,ROW(),'Cash Flows'!$E$2:$E$5628) -> 100.23782 | M10: =L10-J10 -> -0.027124687 | N10: =ABS(M10) -> 0.027124687 | O10: =L10-I10 -> 99.629125 | P10: =IF(AND(O10>=F10,O10<=G10),"Yes","No") -> No
A11: 46341 | B11: 4.625 | C11: 100.04 | D11: 100.05 | E11: 3.741 | F11: =INT(C11)+INT(ROUND((C11-INT(C11))*1000,0)/10)/32+MOD(ROUND((C11-INT(C11))*1000,0),10)/256 -> 100.125 | G11: =INT(D11)+INT(ROUND((D11-INT(D11))*1000,0)/10)/32+MOD(ROUND((D11-INT(D11))*1000,0),10)/256 -> 100.15625 | H11: =(F11+G11)/2 -> 100.14062 | I11: =(B11/2)*COUPDAYBS($R$2,A11,2,1)/COUPDAYS($R$2,A11,2,1) -> 1.4076087 | J11: =H11+I11 -> 101.54823 | K11: =(A11-$R$2)/365 -> 0.19726027 | L11: =SUMIF('Cash Flows'!$A$2:$A$5628,ROW(),'Cash Flows'!$E$2:$E$5628) -> 101.54042 | M11: =L11-J11 -> -0.0078172847 | N11: =ABS(M11) -> 0.0078172847 | O11: =L11-I11 -> 100.13281 | P11: =IF(AND(O11>=F11,O11<=G11),"Yes","No") -> Yes
A12: 46341 | B12: 6.5 | C12: 100.13 | D12: 100.14 | E12: 4.058 | F12: =INT(C12)+INT(ROUND((C12-INT(C12))*1000,0)/10)/32+MOD(ROUND((C12-INT(C12))*1000,0),10)/256 -> 100.40625 | G12: =INT(D12)+INT(ROUND((D12-INT(D12))*1000,0)/10)/32+MOD(ROUND((D12-INT(D12))*1000,0),10)/256 -> 100.4375 | H12: =(F12+G12)/2 -> 100.42188 | I12: =(B12/2)*COUPDAYBS($R$2,A12,2,1)/COUPDAYS($R$2,A12,2,1) -> 1.9782609 | J12: =H12+I12 -> 102.40014 | K12: =(A12-$R$2)/365 -> 0.19726027 | L12: =SUMIF('Cash Flows'!$A$2:$A$5628,ROW(),'Cash Flows'!$E$2:$E$5628) -> 102.47084 | M12: =L12-J12 -> 0.07070586 | N12: =ABS(M12) -> 0.07070586 | O12: =L12-I12 -> 100.49258 | P12: =IF(AND(O12>=F12,O12<=G12),"Yes","No") -> No
A13: 46356 | B13: 1.25 | C13: 99.126 | D13: 99.136 | E13: 3.793 | F13: =INT(C13)+INT(ROUND((C13-INT(C13))*1000,0)/10)/32+MOD(ROUND((C13-INT(C13))*1000,0),10)/256 -> 99.398438 | G13: =INT(D13)+INT(ROUND((D13-INT(D13))*1000,0)/10)/32+MOD(ROUND((D13-INT(D13))*1000,0),10)/256 -> 99.429688 | H13: =(F13+G13)/2 -> 99.414062 | I13: =(B13/2)*COUPDAYBS($R$2,A13,2,1)/COUPDAYS($R$2,A13,2,1) -> 0.32786885 | J13: =H13+I13 -> 99.741931 | K13: =(A13-$R$2)/365 -> 0.23835616 | L13: =SUMIF('Cash Flows'!$A$2:$A$5628,ROW(),'Cash Flows'!$E$2:$E$5628) -> 99.703775 | M13: =L13-J13 -> -0.038155918 | N13: =ABS(M13) -> 0.038155918 | O13: =L13-I13 -> 99.375907 | P13: =IF(AND(O13>=F13,O13<=G13),"Yes","No") -> No
A14: 46356 | B14: 1.625 | C14: 99.156 | D14: 99.166 | E14: 3.747 | F14: =INT(C14)+INT(ROUND((C14-INT(C14))*1000,0)/10)/32+MOD(ROUND((C14-INT(C14))*1000,0),10)/256 -> 99.492188 | G14: =INT(D14)+INT(ROUND((D14-INT(D14))*1000,0)/10)/32+MOD(ROUND((D14-INT(D14))*1000,0),10)/256 -> 99.523438 | H14: =(F14+G14)/2 -> 99.507812 | I14: =(B14/2)*COUPDAYBS($R$2,A14,2,1)/COUPDAYS($R$2,A14,2,1) -> 0.42622951 | J14: =H14+I14 -> 99.934042 | K14: =(A14-$R$2)/365 -> 0.23835616 | L14: =SUMIF('Cash Flows'!$A$2:$A$5628,ROW(),'Cash Flows'!$E$2:$E$5628) -> 99.889559 | M14: =L14-J14 -> -0.044483141 | N14: =ABS(M14) -> 0.044483141 | O14: =L14-I14 -> 99.463329 | P14: =IF(AND(O14>=F14,O14<=G14),"Yes","No") -> No
... A354: 57207 | B354: 5.125 | C354: 98.06 | D354: 98.08 | E354: 5.241 | F354: =INT(C354)+INT(ROUND((C354-INT(C354))*1000,0)/10)/32+MOD(ROUND((C354-INT(C354))*1000,0),10)/256 -> 98.1875 | G354: =INT(D354)+INT(ROUND((D354-INT(D354))*1000,0)/10)/32+MOD(ROUND((D354-INT(D354))*1000,0),10)/256 -> 98.25 | H354: =(F354+G354)/2 -> 98.21875 | I354: =(B354/2)*COUPDAYBS($R$2,A354,2,1)/COUPDAYS($R$2,A354,2,1) -> 0.27853261 | J354: =H354+I354 -> 98.497283 | K354: =(A354-$R$2)/365 -> 29.967123 | L354: =SUMIF('Cash Flows'!$A$2:$A$5628,ROW(),'Cash Flows'!$E$2:$E$5628) -> 98.743894 | M354: =L354-J354 -> 0.24661123 | N354: =ABS(M354) -> 0.24661123 | O354: =L354-I354 -> 98.465361 | P354: =IF(AND(O354>=F354,O354<=G354),"Yes","No") -> No

Sheet Cash Flows
A1: Input Data Row | B1: Payment Date | C1: Cash Flow ($ per $100 face) | D1: Discount Factor | E1: Present Value
A2: 2 | B2: 46280 | C2: =INDEX('Input Data'!$B:$B,A2)/2+IF(A2<>A3,100,0) -> 102.3125 | D2: =INDEX('ZCB Curve - Payment Dates'!$D$2:$D$246,MATCH(B2,'ZCB Curve - Payment Dates'!$A$2:$A$246,0)) -> 0.99886929 | E2: =C2*D2 -> 102.19681
A3: 3 | B3: 46295 | C3: =INDEX('Input Data'!$B:$B,A3)/2+IF(A3<>A4,100,0) -> 100.4375 | D3: =INDEX('ZCB Curve - Payment Dates'!$D$2:$D$246,MATCH(B3,'ZCB Curve - Payment Dates'!$A$2:$A$246,0)) -> 0.9973128 | E3: =C3*D3 -> 100.1676
A4: 4 | B4: 46295 | C4: =INDEX('Input Data'!$B:$B,A4)/2+IF(A4<>A5,100,0) -> 100.8125 | D4: =INDEX('ZCB Curve - Payment Dates'!$D$2:$D$246,MATCH(B4,'ZCB Curve - Payment Dates'!$A$2:$A$246,0)) -> 0.9973128 | E4: =C4*D4 -> 100.5416
A5: 5 | B5: 46295 | C5: =INDEX('Input Data'!$B:$B,A5)/2+IF(A5<>A6,100,0) -> 101.75 | D5: =INDEX('ZCB Curve - Payment Dates'!$D$2:$D$246,MATCH(B5,'ZCB Curve - Payment Dates'!$A$2:$A$246,0)) -> 0.9973128 | E5: =C5*D5 -> 101.47658
A6: 6 | B6: 46310 | C6: =INDEX('Input Data'!$B:$B,A6)/2+IF(A6<>A7,100,0) -> 102.3125 | D6: =INDEX('ZCB Curve - Payment Dates'!$D$2:$D$246,MATCH(B6,'ZCB Curve - Payment Dates'!$A$2:$A$246,0)) -> 0.99574243 | E6: =C6*D6 -> 101.8769
A7: 7 | B7: 46326 | C7: =INDEX('Input Data'!$B:$B,A7)/2+IF(A7<>A8,100,0) -> 100.5625 | D7: =INDEX('ZCB Curve - Payment Dates'!$D$2:$D$246,MATCH(B7,'ZCB Curve - Payment Dates'!$A$2:$A$246,0)) -> 0.99405055 | E7: =C7*D7 -> 99.964209
A8: 8 | B8: 46326 | C8: =INDEX('Input Data'!$B:$B,A8)/2+IF(A8<>A9,100,0) -> 100.8125 | D8: =INDEX('ZCB Curve - Payment Dates'!$D$2:$D$246,MATCH(B8,'ZCB Curve - Payment Dates'!$A$2:$A$246,0)) -> 0.99405055 | E8: =C8*D8 -> 100.21272
A9: 9 | B9: 46326 | C9: =INDEX('Input Data'!$B:$B,A9)/2+IF(A9<>A10,100,0) -> 102.0625 | D9: =INDEX('ZCB Curve - Payment Dates'!$D$2:$D$246,MATCH(B9,'ZCB Curve - Payment Dates'!$A$2:$A$246,0)) -> 0.99405055 | E9: =C9*D9 -> 101.45528
A10: 10 | B10: 46341 | C10: =INDEX('Input Data'!$B:$B,A10)/2+IF(A10<>A11,100,0) -> 101 | D10: =INDEX('ZCB Curve - Payment Dates'!$D$2:$D$246,MATCH(B10,'ZCB Curve - Payment Dates'!$A$2:$A$246,0)) -> 0.99245367 | E10: =C10*D10 -> 100.23782
A11: 11 | B11: 46341 | C11: =INDEX('Input Data'!$B:$B,A11)/2+IF(A11<>A12,100,0) -> 102.3125 | D11: =INDEX('ZCB Curve - Payment Dates'!$D$2:$D$246,MATCH(B11,'ZCB Curve - Payment Dates'!$A$2:$A$246,0)) -> 0.99245367 | E11: =C11*D11 -> 101.54042
A12: 12 | B12: 46341 | C12: =INDEX('Input Data'!$B:$B,A12)/2+IF(A12<>A13,100,0) -> 103.25 | D12: =INDEX('ZCB Curve - Payment Dates'!$D$2:$D$246,MATCH(B12,'ZCB Curve - Payment Dates'!$A$2:$A$246,0)) -> 0.99245367 | E12: =C12*D12 -> 102.47084
A13: 13 | B13: 46356 | C13: =INDEX('Input Data'!$B:$B,A13)/2+IF(A13<>A14,100,0) -> 100.625 | D13: =INDEX('ZCB Curve - Payment Dates'!$D$2:$D$246,MATCH(B13,'ZCB Curve - Payment Dates'!$A$2:$A$246,0)) -> 0.99084497 | E13: =C13*D13 -> 99.703775
... A5628: 354 | B5628: 57207 | C5628: =INDEX('Input Data'!$B:$B,A5628)/2+IF(A5628<>A5629,100,0) -> 102.5625 | D5628: =INDEX('ZCB Curve - Payment Dates'!$D$2:$D$246,MATCH(B5628,'ZCB Curve - Payment Dates'!$A$2:$A$246,0)) -> 0.20798511 | E5628: =C5628*D5628 -> 21.331472

Sheet ZCB Curve - Payment Dates
A1: Payment Date | B1: t (years) | C1: Continuously Compounded Zero Rate | D1: Discount Factor
A2: 46280 | B2: 0.0301 | C2: ='Fit Diagnostics'!$B$4+'Fit Diagnostics'!$B$5*((1-EXP(-B2/'Fit Diagnostics'!$B$8))/(B2/'Fit Diagnostics'!$B$8))+'Fit Diagnostics'!$B$6*(((1-EXP(-B2/'Fit Diagnostics'!$B$8))/(B2/'Fit Diagnostics'!$B$8))-EXP(-B2/'Fit Diagnostics'!$B$8))+'Fit Diagnostics'!$B$7*(((1-EXP(-B2/'Fit Diagnostics'!$B$9))/(B2/'Fit Diagnostics'!$B$9))-EXP(-B2/'Fit Diagnostics'!$B$9)) -> 0.037586353 | D2: =EXP(-C2*B2) -> 0.99886929
A3: 46295 | B3: 0.0712 | C3: ='Fit Diagnostics'!$B$4+'Fit Diagnostics'!$B$5*((1-EXP(-B3/'Fit Diagnostics'!$B$8))/(B3/'Fit Diagnostics'!$B$8))+'Fit Diagnostics'!$B$6*(((1-EXP(-B3/'Fit Diagnostics'!$B$8))/(B3/'Fit Diagnostics'!$B$8))-EXP(-B3/'Fit Diagnostics'!$B$8))+'Fit Diagnostics'!$B$7*(((1-EXP(-B3/'Fit Diagnostics'!$B$9))/(B3/'Fit Diagnostics'!$B$9))-EXP(-B3/'Fit Diagnostics'!$B$9)) -> 0.037792442 | D3: =EXP(-C3*B3) -> 0.9973128
A4: 46310 | B4: 0.1123 | C4: ='Fit Diagnostics'!$B$4+'Fit Diagnostics'!$B$5*((1-EXP(-B4/'Fit Diagnostics'!$B$8))/(B4/'Fit Diagnostics'!$B$8))+'Fit Diagnostics'!$B$6*(((1-EXP(-B4/'Fit Diagnostics'!$B$8))/(B4/'Fit Diagnostics'!$B$8))-EXP(-B4/'Fit Diagnostics'!$B$8))+'Fit Diagnostics'!$B$7*(((1-EXP(-B4/'Fit Diagnostics'!$B$9))/(B4/'Fit Diagnostics'!$B$9))-EXP(-B4/'Fit Diagnostics'!$B$9)) -> 0.037993371 | D4: =EXP(-C4*B4) -> 0.99574243
A5: 46326 | B5: 0.1562 | C5: ='Fit Diagnostics'!$B$4+'Fit Diagnostics'!$B$5*((1-EXP(-B5/'Fit Diagnostics'!$B$8))/(B5/'Fit Diagnostics'!$B$8))+'Fit Diagnostics'!$B$6*(((1-EXP(-B5/'Fit Diagnostics'!$B$8))/(B5/'Fit Diagnostics'!$B$8))-EXP(-B5/'Fit Diagnostics'!$B$8))+'Fit Diagnostics'!$B$7*(((1-EXP(-B5/'Fit Diagnostics'!$B$9))/(B5/'Fit Diagnostics'!$B$9))-EXP(-B5/'Fit Diagnostics'!$B$9)) -> 0.038202416 | D5: =EXP(-C5*B5) -> 0.99405055
A6: 46341 | B6: 0.1973 | C6: ='Fit Diagnostics'!$B$4+'Fit Diagnostics'!$B$5*((1-EXP(-B6/'Fit Diagnostics'!$B$8))/(B6/'Fit Diagnostics'!$B$8))+'Fit Diagnostics'!$B$6*(((1-EXP(-B6/'Fit Diagnostics'!$B$8))/(B6/'Fit Diagnostics'!$B$8))-EXP(-B6/'Fit Diagnostics'!$B$8))+'Fit Diagnostics'!$B$7*(((1-EXP(-B6/'Fit Diagnostics'!$B$9))/(B6/'Fit Diagnostics'!$B$9))-EXP(-B6/'Fit Diagnostics'!$B$9)) -> 0.038393029 | D6: =EXP(-C6*B6) -> 0.99245367
A7: 46356 | B7: 0.2384 | C7: ='Fit Diagnostics'!$B$4+'Fit Diagnostics'!$B$5*((1-EXP(-B7/'Fit Diagnostics'!$B$8))/(B7/'Fit Diagnostics'!$B$8))+'Fit Diagnostics'!$B$6*(((1-EXP(-B7/'Fit Diagnostics'!$B$8))/(B7/'Fit Diagnostics'!$B$8))-EXP(-B7/'Fit Diagnostics'!$B$8))+'Fit Diagnostics'!$B$7*(((1-EXP(-B7/'Fit Diagnostics'!$B$9))/(B7/'Fit Diagnostics'!$B$9))-EXP(-B7/'Fit Diagnostics'!$B$9)) -> 0.038578824 | D7: =EXP(-C7*B7) -> 0.99084497
A8: 46371 | B8: 0.2795 | C8: ='Fit Diagnostics'!$B$4+'Fit Diagnostics'!$B$5*((1-EXP(-B8/'Fit Diagnostics'!$B$8))/(B8/'Fit Diagnostics'!$B$8))+'Fit Diagnostics'!$B$6*(((1-EXP(-B8/'Fit Diagnostics'!$B$8))/(B8/'Fit Diagnostics'!$B$8))-EXP(-B8/'Fit Diagnostics'!$B$8))+'Fit Diagnostics'!$B$7*(((1-EXP(-B8/'Fit Diagnostics'!$B$9))/(B8/'Fit Diagnostics'!$B$9))-EXP(-B8/'Fit Diagnostics'!$B$9)) -> 0.038759906 | D8: =EXP(-C8*B8) -> 0.98922508
A9: 46387 | B9: 0.3233 | C9: ='Fit Diagnostics'!$B$4+'Fit Diagnostics'!$B$5*((1-EXP(-B9/'Fit Diagnostics'!$B$8))/(B9/'Fit Diagnostics'!$B$8))+'Fit Diagnostics'!$B$6*(((1-EXP(-B9/'Fit Diagnostics'!$B$8))/(B9/'Fit Diagnostics'!$B$8))-EXP(-B9/'Fit Diagnostics'!$B$8))+'Fit Diagnostics'!$B$7*(((1-EXP(-B9/'Fit Diagnostics'!$B$9))/(B9/'Fit Diagnostics'!$B$9))-EXP(-B9/'Fit Diagnostics'!$B$9)) -> 0.038947816 | D9: =EXP(-C9*B9) -> 0.98748712
A10: 46402 | B10: 0.3644 | C10: ='Fit Diagnostics'!$B$4+'Fit Diagnostics'!$B$5*((1-EXP(-B10/'Fit Diagnostics'!$B$8))/(B10/'Fit Diagnostics'!$B$8))+'Fit Diagnostics'!$B$6*(((1-EXP(-B10/'Fit Diagnostics'!$B$8))/(B10/'Fit Diagnostics'!$B$8))-EXP(-B10/'Fit Diagnostics'!$B$8))+'Fit Diagnostics'!$B$7*(((1-EXP(-B10/'Fit Diagnostics'!$B$9))/(B10/'Fit Diagnostics'!$B$9))-EXP(-B10/'Fit Diagnostics'!$B$9)) -> 0.039119497 | D10: =EXP(-C10*B10) -> 0.98584598
A11: 46418 | B11: 0.4082 | C11: ='Fit Diagnostics'!$B$4+'Fit Diagnostics'!$B$5*((1-EXP(-B11/'Fit Diagnostics'!$B$8))/(B11/'Fit Diagnostics'!$B$8))+'Fit Diagnostics'!$B$6*(((1-EXP(-B11/'Fit Diagnostics'!$B$8))/(B11/'Fit Diagnostics'!$B$8))-EXP(-B11/'Fit Diagnostics'!$B$8))+'Fit Diagnostics'!$B$7*(((1-EXP(-B11/'Fit Diagnostics'!$B$9))/(B11/'Fit Diagnostics'!$B$9))-EXP(-B11/'Fit Diagnostics'!$B$9)) -> 0.039297619 | D11: =EXP(-C11*B11) -> 0.98408669
A12: 46433 | B12: 0.4493 | C12: ='Fit Diagnostics'!$B$4+'Fit Diagnostics'!$B$5*((1-EXP(-B12/'Fit Diagnostics'!$B$8))/(B12/'Fit Diagnostics'!$B$8))+'Fit Diagnostics'!$B$6*(((1-EXP(-B12/'Fit Diagnostics'!$B$8))/(B12/'Fit Diagnostics'!$B$8))-EXP(-B12/'Fit Diagnostics'!$B$8))+'Fit Diagnostics'!$B$7*(((1-EXP(-B12/'Fit Diagnostics'!$B$9))/(B12/'Fit Diagnostics'!$B$9))-EXP(-B12/'Fit Diagnostics'!$B$9)) -> 0.039460328 | D12: =EXP(-C12*B12) -> 0.98242672
A13: 46446 | B13: 0.4849 | C13: ='Fit Diagnostics'!$B$4+'Fit Diagnostics'!$B$5*((1-EXP(-B13/'Fit Diagnostics'!$B$8))/(B13/'Fit Diagnostics'!$B$8))+'Fit Diagnostics'!$B$6*(((1-EXP(-B13/'Fit Diagnostics'!$B$8))/(B13/'Fit Diagnostics'!$B$8))-EXP(-B13/'Fit Diagnostics'!$B$8))+'Fit Diagnostics'!$B$7*(((1-EXP(-B13/'Fit Diagnostics'!$B$9))/(B13/'Fit Diagnostics'!$B$9))-EXP(-B13/'Fit Diagnostics'!$B$9)) -> 0.039597871 | D13: =EXP(-C13*B13) -> 0.98098216
... A246: 57207 | B246: 29.9671 | C246: ='Fit Diagnostics'!$B$4+'Fit Diagnostics'!$B$5*((1-EXP(-B246/'Fit Diagnostics'!$B$8))/(B246/'Fit Diagnostics'!$B$8))+'Fit Diagnostics'!$B$6*(((1-EXP(-B246/'Fit Diagnostics'!$B$8))/(B246/'Fit Diagnostics'!$B$8))-EXP(-B246/'Fit Diagnostics'!$B$8))+'Fit Diagnostics'!$B$7*(((1-EXP(-B246/'Fit Diagnostics'!$B$9))/(B246/'Fit Diagnostics'!$B$9))-EXP(-B246/'Fit Diagnostics'!$B$9)) -> 0.052400426 | D246: =EXP(-C246*B246) -> 0.20798511

Sheet ZCB Curve - Smooth Grid
A1: t (years) | B1: Continuously Compounded Zero Rate | C1: Discount Factor
A2: 0.1 | B2: ='Fit Diagnostics'!$B$4+'Fit Diagnostics'!$B$5*((1-EXP(-A2/'Fit Diagnostics'!$B$8))/(A2/'Fit Diagnostics'!$B$8))+'Fit Diagnostics'!$B$6*(((1-EXP(-A2/'Fit Diagnostics'!$B$8))/(A2/'Fit Diagnostics'!$B$8))-EXP(-A2/'Fit Diagnostics'!$B$8))+'Fit Diagnostics'!$B$7*(((1-EXP(-A2/'Fit Diagnostics'!$B$9))/(A2/'Fit Diagnostics'!$B$9))-EXP(-A2/'Fit Diagnostics'!$B$9)) -> 0.037933773 | C2: =EXP(-B2*A2) -> 0.99621381
A3: 0.2 | B3: ='Fit Diagnostics'!$B$4+'Fit Diagnostics'!$B$5*((1-EXP(-A3/'Fit Diagnostics'!$B$8))/(A3/'Fit Diagnostics'!$B$8))+'Fit Diagnostics'!$B$6*(((1-EXP(-A3/'Fit Diagnostics'!$B$8))/(A3/'Fit Diagnostics'!$B$8))-EXP(-A3/'Fit Diagnostics'!$B$8))+'Fit Diagnostics'!$B$7*(((1-EXP(-A3/'Fit Diagnostics'!$B$9))/(A3/'Fit Diagnostics'!$B$9))-EXP(-A3/'Fit Diagnostics'!$B$9)) -> 0.038405381 | C3: =EXP(-B3*A3) -> 0.99234835
A4: 0.3 | B4: ='Fit Diagnostics'!$B$4+'Fit Diagnostics'!$B$5*((1-EXP(-A4/'Fit Diagnostics'!$B$8))/(A4/'Fit Diagnostics'!$B$8))+'Fit Diagnostics'!$B$6*(((1-EXP(-A4/'Fit Diagnostics'!$B$8))/(A4/'Fit Diagnostics'!$B$8))-EXP(-A4/'Fit Diagnostics'!$B$8))+'Fit Diagnostics'!$B$7*(((1-EXP(-A4/'Fit Diagnostics'!$B$9))/(A4/'Fit Diagnostics'!$B$9))-EXP(-A4/'Fit Diagnostics'!$B$9)) -> 0.038848499 | C4: =EXP(-B4*A4) -> 0.9884131
A5: 0.4 | B5: ='Fit Diagnostics'!$B$4+'Fit Diagnostics'!$B$5*((1-EXP(-A5/'Fit Diagnostics'!$B$8))/(A5/'Fit Diagnostics'!$B$8))+'Fit Diagnostics'!$B$6*(((1-EXP(-A5/'Fit Diagnostics'!$B$8))/(A5/'Fit Diagnostics'!$B$8))-EXP(-A5/'Fit Diagnostics'!$B$8))+'Fit Diagnostics'!$B$7*(((1-EXP(-A5/'Fit Diagnostics'!$B$9))/(A5/'Fit Diagnostics'!$B$9))-EXP(-A5/'Fit Diagnostics'!$B$9)) -> 0.039264646 | C5: =EXP(-B5*A5) -> 0.98441684
A6: 0.5 | B6: ='Fit Diagnostics'!$B$4+'Fit Diagnostics'!$B$5*((1-EXP(-A6/'Fit Diagnostics'!$B$8))/(A6/'Fit Diagnostics'!$B$8))+'Fit Diagnostics'!$B$6*(((1-EXP(-A6/'Fit Diagnostics'!$B$8))/(A6/'Fit Diagnostics'!$B$8))-EXP(-A6/'Fit Diagnostics'!$B$8))+'Fit Diagnostics'!$B$7*(((1-EXP(-A6/'Fit Diagnostics'!$B$9))/(A6/'Fit Diagnostics'!$B$9))-EXP(-A6/'Fit Diagnostics'!$B$9)) -> 0.039655276 | C6: =EXP(-B6*A6) -> 0.98036764
A7: 0.6 | B7: ='Fit Diagnostics'!$B$4+'Fit Diagnostics'!$B$5*((1-EXP(-A7/'Fit Diagnostics'!$B$8))/(A7/'Fit Diagnostics'!$B$8))+'Fit Diagnostics'!$B$6*(((1-EXP(-A7/'Fit Diagnostics'!$B$8))/(A7/'Fit Diagnostics'!$B$8))-EXP(-A7/'Fit Diagnostics'!$B$8))+'Fit Diagnostics'!$B$7*(((1-EXP(-A7/'Fit Diagnostics'!$B$9))/(A7/'Fit Diagnostics'!$B$9))-EXP(-A7/'Fit Diagnostics'!$B$9)) -> 0.040021775 | C7: =EXP(-B7*A7) -> 0.97627295
A8: 0.7 | B8: ='Fit Diagnostics'!$B$4+'Fit Diagnostics'!$B$5*((1-EXP(-A8/'Fit Diagnostics'!$B$8))/(A8/'Fit Diagnostics'!$B$8))+'Fit Diagnostics'!$B$6*(((1-EXP(-A8/'Fit Diagnostics'!$B$8))/(A8/'Fit Diagnostics'!$B$8))-EXP(-A8/'Fit Diagnostics'!$B$8))+'Fit Diagnostics'!$B$7*(((1-EXP(-A8/'Fit Diagnostics'!$B$9))/(A8/'Fit Diagnostics'!$B$9))-EXP(-A8/'Fit Diagnostics'!$B$9)) -> 0.040365465 | C8: =EXP(-B8*A8) -> 0.97213964
A9: 0.8 | B9: ='Fit Diagnostics'!$B$4+'Fit Diagnostics'!$B$5*((1-EXP(-A9/'Fit Diagnostics'!$B$8))/(A9/'Fit Diagnostics'!$B$8))+'Fit Diagnostics'!$B$6*(((1-EXP(-A9/'Fit Diagnostics'!$B$8))/(A9/'Fit Diagnostics'!$B$8))-EXP(-A9/'Fit Diagnostics'!$B$8))+'Fit Diagnostics'!$B$7*(((1-EXP(-A9/'Fit Diagnostics'!$B$9))/(A9/'Fit Diagnostics'!$B$9))-EXP(-A9/'Fit Diagnostics'!$B$9)) -> 0.040687609 | C9: =EXP(-B9*A9) -> 0.96797397
A10: 0.9 | B10: ='Fit Diagnostics'!$B$4+'Fit Diagnostics'!$B$5*((1-EXP(-A10/'Fit Diagnostics'!$B$8))/(A10/'Fit Diagnostics'!$B$8))+'Fit Diagnostics'!$B$6*(((1-EXP(-A10/'Fit Diagnostics'!$B$8))/(A10/'Fit Diagnostics'!$B$8))-EXP(-A10/'Fit Diagnostics'!$B$8))+'Fit Diagnostics'!$B$7*(((1-EXP(-A10/'Fit Diagnostics'!$B$9))/(A10/'Fit Diagnostics'!$B$9))-EXP(-A10/'Fit Diagnostics'!$B$9)) -> 0.040989412 | C10: =EXP(-B10*A10) -> 0.96378169
A11: 1 | B11: ='Fit Diagnostics'!$B$4+'Fit Diagnostics'!$B$5*((1-EXP(-A11/'Fit Diagnostics'!$B$8))/(A11/'Fit Diagnostics'!$B$8))+'Fit Diagnostics'!$B$6*(((1-EXP(-A11/'Fit Diagnostics'!$B$8))/(A11/'Fit Diagnostics'!$B$8))-EXP(-A11/'Fit Diagnostics'!$B$8))+'Fit Diagnostics'!$B$7*(((1-EXP(-A11/'Fit Diagnostics'!$B$9))/(A11/'Fit Diagnostics'!$B$9))-EXP(-A11/'Fit Diagnostics'!$B$9)) -> 0.041272021 | C11: =EXP(-B11*A11) -> 0.95956807
A12: 1.1 | B12: ='Fit Diagnostics'!$B$4+'Fit Diagnostics'!$B$5*((1-EXP(-A12/'Fit Diagnostics'!$B$8))/(A12/'Fit Diagnostics'!$B$8))+'Fit Diagnostics'!$B$6*(((1-EXP(-A12/'Fit Diagnostics'!$B$8))/(A12/'Fit Diagnostics'!$B$8))-EXP(-A12/'Fit Diagnostics'!$B$8))+'Fit Diagnostics'!$B$7*(((1-EXP(-A12/'Fit Diagnostics'!$B$9))/(A12/'Fit Diagnostics'!$B$9))-EXP(-A12/'Fit Diagnostics'!$B$9)) -> 0.041536532 | C12: =EXP(-B12*A12) -> 0.95533789
A13: 1.2 | B13: ='Fit Diagnostics'!$B$4+'Fit Diagnostics'!$B$5*((1-EXP(-A13/'Fit Diagnostics'!$B$8))/(A13/'Fit Diagnostics'!$B$8))+'Fit Diagnostics'!$B$6*(((1-EXP(-A13/'Fit Diagnostics'!$B$8))/(A13/'Fit Diagnostics'!$B$8))-EXP(-A13/'Fit Diagnostics'!$B$8))+'Fit Diagnostics'!$B$7*(((1-EXP(-A13/'Fit Diagnostics'!$B$9))/(A13/'Fit Diagnostics'!$B$9))-EXP(-A13/'Fit Diagnostics'!$B$9)) -> 0.041783989 | C13: =EXP(-B13*A13) -> 0.95109551
... A301: 30 | B301: ='Fit Diagnostics'!$B$4+'Fit Diagnostics'!$B$5*((1-EXP(-A301/'Fit Diagnostics'!$B$8))/(A301/'Fit Diagnostics'!$B$8))+'Fit Diagnostics'!$B$6*(((1-EXP(-A301/'Fit Diagnostics'!$B$8))/(A301/'Fit Diagnostics'!$B$8))-EXP(-A301/'Fit Diagnostics'!$B$8))+'Fit Diagnostics'!$B$7*(((1-EXP(-A301/'Fit Diagnostics'!$B$9))/(A301/'Fit Diagnostics'!$B$9))-EXP(-A301/'Fit Diagnostics'!$B$9)) -> 0.052384756 | C301: =EXP(-B301*A301) -> 0.20772448

Sheet Curve Chart

Sheet Fit Diagnostics
A1: NSS Fit Diagnostics & Validation
A3: NSS Parameter | B3: Value | C3: Interpretation | E3: Fit Metric | F3: Result
A4: β0 | B4: -0.073402707 | C4: Long-run level | E4: Price RMSE ($ per $100 face) | F4: =SQRT(SUMPRODUCT('Input Data'!M2:M354,'Input Data'!M2:M354)/COUNT('Input Data'!M2:M354)) -> 0.14751439
A5: β1 | B5: 0.11083479 | C5: Short-end slope | E5: Mean absolute error ($) | F5: =AVERAGE('Input Data'!N2:N354) -> 0.088659025
A6: β2 | B6: 0.082040702 | C6: First curvature term | E6: Maximum absolute error ($) | F6: =MAX('Input Data'!N2:N354) -> 0.94838904
A7: β3 | B7: 0.36280714 | C7: Second curvature term | E7: Bonds priced inside bid-ask | F7: =COUNTIF('Input Data'!P2:P354,"Yes")/COUNTA('Input Data'!P2:P354) -> 0.18696884
A8: τ1 | B8: 2.7344509 | C8: Decay parameter 1 (years) | E8: Number of bonds | F8: =COUNT('Input Data'!A2:A354) -> 353
A9: τ2 | B9: 17.379328 | C9: Decay parameter 2 (years)
A11: Validation notes
A12: Treasury quotes were decoded using the standard 32nds-plus-eighths convention (e.g. a quoted 99.312 means 99 + (31 + 2/8)/32 = 99.9765625), not a literal decimal reading. The literal-decimal reading used in the prior workbook understated most bid/ask prices by an average of about 0.34 points, with the largest distortion at the short end of the curve.
A13: Coupon payment dates were regenerated bond-by-bond, stepping back six months at a time from each bond's maturity and preserving month-end dates when the maturity itself falls on the last day of a month. This produces 245 distinct future payment dates across the 353 bonds (the prior workbook's 282-date table did not preserve month-end dates and is not used).
A14: Accrued interest uses Excel's COUPDAYBS/COUPDAYS functions (Actual/Actual, semiannual) off the settlement date in Input Data!R2, which read the same month-end-consistent coupon schedule as the payment-date list.
A15: The fitted curve was re-priced bond-by-bond by summing each bond's own discounted cash flows ('Cash Flows' sheet, 5,627 rows) against the live discount factors on 'ZCB Curve - Payment Dates' -- Model Dirty Price is a live SUMIF formula, not a pasted value. Minimizing summed squared price residuals (unweighted) against the corrected dirty prices, the reproduced RMSE is about $0.148 per $100 face, versus $0.293 for the prior (mis-decoded) fit. Six-parameter NSS fits are multi-modal; these parameters were selected from a multistart nonlinear least-squares search (60+ starting points converging to the same minimum) run outside Excel, since Excel has no native nonlinear solver -- the six parameters below are the only inputs in the workbook that are not native formulas.
A16: A price-based objective implicitly weights a given yield error by (price x modified duration), so it is more forgiving of short-maturity yield noise than a yield-based objective would be. That is a modeling trade-off, not a defect, and is documented here rather than left implicit.
A17: Model / assignment alignment
A18: The assignment (Lecture 2B, slide 35) asks for a detailed automated algorithm giving the continuously compounded discount rate for each bond payment date, in the form of a function and a graph, with a methodology write-up under one page. NSS is a valid smooth whole-curve approach for this; the workbook keeps the fitted parameters, curve formulas, quote decoding, and pricing diagnostics all visible and auditable.
